agents_sdk_mutta/__init__.py
agents_sdk_mutta/cli.py
agents_sdk_mutta/py.typed
agents_sdk_mutta/commands/__init__.py
agents_sdk_mutta/commands/startproject.py
agents_sdk_mutta/commands/startservice.py
agents_sdk_mutta/rules/__init__.py
agents_sdk_mutta/rules/agent-additional.mdc
agents_sdk_mutta/rules/agent_services.mdc
agents_sdk_mutta/rules/mutta-cli.mdc
agents_sdk_mutta/rules/openai-agents-sdk.mdc
agents_sdk_mutta/templates/__init__.py
agents_sdk_mutta/templates/agents_sdk_readme.py
agents_sdk_mutta/templates/service_templates.py
agents_sdk_mutta/templates/usage_tracking.py
agents_sdk_mutta-0.1.1.dist-info/METADATA
agents_sdk_mutta-0.1.1.dist-info/WHEEL
agents_sdk_mutta-0.1.1.dist-info/entry_points.txt
agents_sdk_mutta-0.1.1.dist-info/licenses/LICENSE
agents_sdk_mutta-0.1.1.dist-info/RECORD
