Metadata-Version: 2.4
Name: agents-sdk-mutta
Version: 0.1.1
Summary: CLI scaffolding tool for OpenAI Agents SDK projects following Mutta conventions
Project-URL: Homepage, https://github.com/maestromaximo/agent-sdk-mutta
Project-URL: Documentation, https://github.com/maestromaximo/agent-sdk-mutta#readme
Project-URL: Repository, https://github.com/maestromaximo/agent-sdk-mutta
Project-URL: Bug Tracker, https://github.com/maestromaximo/agent-sdk-mutta/issues
Project-URL: Changelog, https://github.com/maestromaximo/agent-sdk-mutta/releases
Author-email: Alejandro Garcia Polo <alejandrogarcia2423@hotmail.com>
Maintainer-email: Alejandro Garcia Polo <alejandrogarcia2423@hotmail.com>
License-Expression: PolyForm-Noncommercial-1.0.0
License-File: LICENSE
Keywords: agents,ai,cli,llm,mutta,openai,scaffolding,sdk
Classifier: Development Status :: 3 - Alpha
Classifier: Intended Audience :: Developers
Classifier: License :: Other/Proprietary License
Classifier: Programming Language :: Python :: 3
Classifier: Programming Language :: Python :: 3.10
Classifier: Programming Language :: Python :: 3.11
Classifier: Programming Language :: Python :: 3.12
Classifier: Programming Language :: Python :: 3.13
Classifier: Topic :: Software Development :: Code Generators
Classifier: Topic :: Software Development :: Libraries :: Python Modules
Classifier: Typing :: Typed
Requires-Python: >=3.10
Requires-Dist: click>=8.0.0
Requires-Dist: rich>=13.0.0
Provides-Extra: dev
Requires-Dist: pytest-cov>=4.0.0; extra == 'dev'
Requires-Dist: pytest>=7.0.0; extra == 'dev'
